anc_data/__init__.py
anc_data/anc_composer.py
anc_data/anc_dataloader.py
anc_data/anc_dataset.py
anc_data/anc_processor.py
anc_data/anc_sampler.py
anc_data/blob_dataset.py
anc_data/bucketed_dataset.py
anc_data/jsonl_dataset.py
anc_data/parquet_dataset.py
anc_data/processors/llm_processor.py
anc_data/processors/tokenizer.py
anc_data/utils/data_states.py
anc_data/utils/memory.py
anc_data/utils/parquet_dataset_metadata_gen.py
anc_data-0.1.32.dist-info/METADATA
anc_data-0.1.32.dist-info/WHEEL
anc_data-0.1.32.dist-info/RECORD
